MANIFEST.in
README.md
VERSION
requirements.txt
setup.py
raspi_logger/CONFIG.JSON
raspi_logger/__init__.py
raspi_logger/__main__.py
raspi_logger/api.py
raspi_logger/keywords.py
raspi_logger/logger.py
raspi_logger/main.py
raspi_logger/util.py
raspi_logger.egg-info/PKG-INFO
raspi_logger.egg-info/SOURCES.txt
raspi_logger.egg-info/dependency_links.txt
raspi_logger.egg-info/entry_points.txt
raspi_logger.egg-info/not-zip-safe
raspi_logger.egg-info/requires.txt
raspi_logger.egg-info/top_level.txt
raspi_logger/backends/__init__.py
raspi_logger/backends/json_backend.py
raspi_logger/backends/sqlite_backend.py
raspi_logger/sensors/__init__.py
raspi_logger/sensors/ds18b20.py