Metadata-Version: 2.1
Name: raspi-logger
Version: 0.3.0
Summary: Raspberry Pi data logging software toolkit
Home-page: UNKNOWN
Author: Mirko Mälicke
Author-email: mirko@hydrocode.de
License: UNKNOWN
Platform: UNKNOWN
